simplify/__init__.py
simplify/benchmark.py
simplify/configuration.py
simplify/exceptions.py
simplify/fitter.py
simplify/model_tools.py
simplify/plot.py
simplify/simplified.py
simplify/version.py
simplify/yields.py
simplify/cli/__init__.py
simplify/helpers/__init__.py
simplify/helpers/plotting.py
simplify_hep-0.1.5.dist-info/LICENSE
simplify_hep-0.1.5.dist-info/METADATA
simplify_hep-0.1.5.dist-info/WHEEL
simplify_hep-0.1.5.dist-info/entry_points.txt
simplify_hep-0.1.5.dist-info/top_level.txt
simplify_hep-0.1.5.dist-info/RECORD
