Metadata-Version: 2.1
Name: simplify-hep
Version: 0.1.5
Summary: Produce simplified likelihoods of different formats
Home-page: UNKNOWN
Author: Eric Schanet
License: BSD 3-Clause
Project-URL: Source, https://github.com/eschanet/simplify
Project-URL: Tracker, https://github.com/eschanet/simplify/issues
Platform: UNKNOWN
Classifier: Development Status :: 3 - Alpha
Classifier: Programming Language :: Python :: 3.6
Classifier: Programming Language :: Python :: 3.7
Classifier: Programming Language :: Python :: 3.8
Classifier: License :: OSI Approved :: BSD License
Classifier: Topic :: Scientific/Engineering
Classifier: Topic :: Scientific/Engineering :: Physics
Classifier: Intended Audience :: Science/Research
Requires-Python: >=3.6
Requires-Dist: pyhf[minuit] (==0.5.4)
Requires-Dist: boost-histogram
Requires-Dist: awkward1
Provides-Extra: complete
Requires-Dist: black ; extra == 'complete'
Requires-Dist: bump2version ; extra == 'complete'
Requires-Dist: flake8 ; extra == 'complete'
Requires-Dist: flake8-bugbear ; extra == 'complete'
Requires-Dist: flake8-import-order ; extra == 'complete'
Requires-Dist: flake8-print ; extra == 'complete'
Requires-Dist: matplotlib ; extra == 'complete'
Requires-Dist: mypy ; extra == 'complete'
Requires-Dist: pre-commit ; extra == 'complete'
Requires-Dist: pydocstyle ; extra == 'complete'
Requires-Dist: pytest ; extra == 'complete'
Requires-Dist: pytest-cov (>=2.5.1) ; extra == 'complete'
Requires-Dist: twine ; extra == 'complete'
Requires-Dist: typeguard ; extra == 'complete'
Provides-Extra: contrib
Requires-Dist: matplotlib ; extra == 'contrib'
Provides-Extra: develop
Requires-Dist: black ; extra == 'develop'
Requires-Dist: bump2version ; extra == 'develop'
Requires-Dist: flake8 ; extra == 'develop'
Requires-Dist: flake8-bugbear ; extra == 'develop'
Requires-Dist: flake8-import-order ; extra == 'develop'
Requires-Dist: flake8-print ; extra == 'develop'
Requires-Dist: matplotlib ; extra == 'develop'
Requires-Dist: mypy ; extra == 'develop'
Requires-Dist: pre-commit ; extra == 'develop'
Requires-Dist: pydocstyle ; extra == 'develop'
Requires-Dist: pytest ; extra == 'develop'
Requires-Dist: pytest-cov (>=2.5.1) ; extra == 'develop'
Requires-Dist: twine ; extra == 'develop'
Requires-Dist: typeguard ; extra == 'develop'
Provides-Extra: test
Requires-Dist: black ; extra == 'test'
Requires-Dist: flake8 ; extra == 'test'
Requires-Dist: flake8-bugbear ; extra == 'test'
Requires-Dist: flake8-import-order ; extra == 'test'
Requires-Dist: flake8-print ; extra == 'test'
Requires-Dist: matplotlib ; extra == 'test'
Requires-Dist: mypy ; extra == 'test'
Requires-Dist: pydocstyle ; extra == 'test'
Requires-Dist: pytest ; extra == 'test'
Requires-Dist: pytest-cov (>=2.5.1) ; extra == 'test'
Requires-Dist: typeguard ; extra == 'test'
